{
  "_meta": {
    "title": "리이오가 다뤄볼 문제 (Opportunity Map)",
    "desc": "리이오의 기존 31개 앱과 겹치지 않으면서, 작은 iOS/macOS 앱으로 실현 가능한 문제. 미세불편(🧩)·정의된문제(📐)에서 파생하거나 미개척 신규도메인(🆕). 문제 p는 {pain,who,when,gap}, gap 끝에 '리이오 강점' 적합성 표기. index.html D 스키마 호환.",
    "tags": "🧩=미세불편 파생 · 📐=정의된문제 파생 · 🆕=신규 도메인",
    "based_on": "D_MICRO, D_DEFINED, D_LEEO 교차분석",
    "generated": "2026-07-16",
    "updated": "2026-07-19 (2차 확장: 기존 10도메인 내 74개)"
  },
  "D": [
    {
      "id": "opp-scan", "icon": "📸", "title": "기록·스캔 (미개척)", "color": "#6c5ce7",
      "subs": [
        {
          "title": "🌱 다뤄볼 만한 것",
          "ep": [
            {"n": "🧩 반듯 — 슬라이드·판서 자동 보정", "p": [{"pain": "강연·수업서 찍은 사진이 사다리꼴에 테두리까지 나와 매번 크롭·리사이즈", "who": "대학생·강연 자주 듣는 직장인", "when": "강의 슬라이드·화이트보드를 찍어 모을 때", "gap": "기본 카메라는 원근보정 없음 · 리이오 강점: 픽셀미미/펀칭의 사진처리 + 앨범 정리·위젯"}]},
            {"n": "🧩 널널노트 — 필기 사진 과목·날짜 자동 앨범", "p": [{"pain": "손글씨 노트·교재 사진이 'Screenshot_날짜'로만 남아 나중에 못 찾음", "who": "필기를 사진으로 남기는 학생", "when": "시험기간 특정 개념을 찾을 때", "gap": "갤러리는 과목·주차 분류 없음 · 리이오 강점: 태그·기록·검색 UX"}]},
            {"n": "🧩 찰칵정리 — 스크린샷 자동 분류·만료 정리", "p": [{"pain": "와이파이 비번·예약번호·계좌를 스크린샷으로 남기지만 수천 장에 묻혀 못 찾고, 쓸모 끝난 것도 계속 쌓임", "who": "뭐든 일단 스크린샷으로 찍어두는 사람", "when": "찍어둔 정보가 급히 필요할 때·저장공간 정리할 때", "gap": "갤러리는 용도별 분류·유효기간 개념 없음 · 리이오 강점: 사진 정리 UX + 클립키보드(정보 재사용) 인접"}]},
            {"n": "🧩 책갈피샷 — 책 구절 촬영→문장 스크랩", "p": [{"pain": "책 좋은 구절을 찍어둬도 갤러리에 묻혀 다시 안 보고, 어느 책 몇 쪽인지도 기억 안 남", "who": "종이책 읽으며 밑줄 대신 사진 찍는 독서가", "when": "독서 중 남기고 싶은 문장을 만날 때", "gap": "갤러리는 책별·주제별 모아보기 없음 · 리이오 강점: 사진처리 + 기록·회고(리바운드 저널) UX"}]},
            {"n": "🧩 명함한장 — 명함 촬영→연락처·만난 맥락 저장", "p": [{"pain": "명함을 받아도 연락처 입력이 수동이고, 나중엔 이 사람을 어디서 만났는지 기억 안 남", "who": "미팅·행사 많은 직장인·프리랜서", "when": "명함을 받고 지갑에 쌓일 때", "gap": "명함앱은 회사·계정 종속에 무거움 · 리이오 강점: 사진처리 + 라포 맵(관계 맥락 기록) 인접"}]},
            {"n": "🧩 낙서보관 — 아이 그림·작품 연도별 아카이브", "p": [{"pain": "아이 그림·만들기가 쌓여 버리자니 아깝고 두자니 짐인데, 찍어둔 사진도 갤러리에 섞여버림", "who": "유치원·초등 자녀를 둔 부모", "when": "학기말 작품 뭉치를 들고 올 때", "gap": "갤러리는 아이별·연도별 작품 앨범이 수동 · 리이오 강점: 사진 정리 + 성장 기록 시각화"}]},
            {"n": "🧩 계약서철 — 계약서·보증서 촬영 보관·만료 알림", "p": [{"pain": "전세계약서·가전 보증서를 찍어놔도 못 찾고, 보증기간은 지나고 나서야 확인", "who": "계약·보증 서류가 쌓이는 1인 가구·가장", "when": "AS 맡기거나 계약 갱신할 때", "gap": "갤러리·파일앱엔 만료일 개념 없음 · 리이오 강점: 스캔 + 두번알림(만료 전 알림)"}]},
            {"n": "🧩 앨범다이어트 — 연사·중복·흔들린 사진 정리", "p": [{"pain": "비슷한 연사 수십 장이 용량을 차지하는데 하나씩 비교하며 지우는 게 일", "who": "사진이 수만 장 쌓인 아이폰 사용자", "when": "저장공간 부족 경고가 뜰 때", "gap": "기본 정리 기능은 중복 감지가 얕음 · 리이오 강점: 픽셀미미/펀칭 사진처리 노하우 + 비교 UX"}]}
          ]
        }
      ]
    },
    {
      "id": "opp-kitchen", "icon": "🍳", "title": "주방·요리 (미개척)", "color": "#e17055",
      "subs": [
        {
          "title": "🌱 다뤄볼 만한 것",
          "ep": [
            {"n": "🧩 동시냄비 — 라벨 붙은 멀티 요리 타이머", "p": [{"pain": "밥·국·구이 동시 조리 시 기본 타이머는 하나뿐이라 지우고 새로 설정, 뭐가 뭔지 헷갈림", "who": "집에서 여러 요리 동시에 하는 사람", "when": "여러 냄비를 동시에 올릴 때", "gap": "기본 타이머는 단일·무라벨 · 리이오 강점: StickyPresenter 타이머 노하우 + 위젯"}]},
            {"n": "🧩 언제까지 — 밀프렙·남은음식 유통기한 위젯", "p": [{"pain": "소분한 반찬·남은 배달음식이 언제까지인지 몰라 상해서 버림", "who": "밀프렙·자취·냉장고 관리하는 사람", "when": "먹을지 말지 매번 고민할 때", "gap": "통마다 손으로 날짜 적기 귀찮음 · 리이오 강점: 클로즈드(장보기)·두번알림 인접, 위젯"}]},
            {"n": "🧩 몇그램 — 재료별 계량·인분 스케일러", "p": [{"pain": "컵↔그램이 재료마다 밀도가 달라 안 맞고, 2인분→1인분 계란 0.5개 애매", "who": "레시피 따라 요리·베이킹하는 사람", "when": "분량을 줄이거나 단위 바꿀 때", "gap": "일반 계산기는 재료 밀도 모름 · 리이오 강점: 확률계산기류 유틸 설계"}]},
            {"n": "🧩 대체재료 — 없는 재료 대체 비율 치트시트", "p": [{"pain": "요리 중 버터·맛술·생크림이 없어 젖은 손으로 '○○ 대체' 검색, 블로그마다 비율이 달라 헷갈림", "who": "있는 재료로 어떻게든 만드는 자취생·홈쿡", "when": "조리 중 재료 하나가 없다는 걸 깨달았을 때", "gap": "검색 결과는 광고·긴 글 속에 비율이 숨어 있음 · 리이오 강점: 오프라인 원탭 유틸 + 확률계산기류 변환 설계"}]},
            {"n": "🧩 담근날 — 발효·숙성 D+일 추적", "p": [{"pain": "김치·요거트·과실주·빵 반죽을 언제 담갔는지 기억 안 나 맛볼 타이밍을 놓치거나 시어버림", "who": "발효·저장식 만드는 사람, 홈베이커", "when": "담근 지 며칠째인지 확인할 때", "gap": "캘린더는 '경과일 카운트업'에 안 맞음 · 리이오 강점: D+일 기록·두번알림·위젯"}]},
            {"n": "🧩 에프환산 — 오븐 레시피→에어프라이어 변환", "p": [{"pain": "레시피는 죄다 오븐 기준인데 우리집엔 에어프라이어뿐, 몇 도 몇 분인지 매번 검색", "who": "에어프라이어로 요리하는 자취생·가정", "when": "오븐 레시피를 따라 할 때", "gap": "변환 규칙이 흩어져 있고 기종별 편차 메모도 못 함 · 리이오 강점: 확률계산기류 변환 유틸 + 타이머"}]},
            {"n": "🧩 밥물비율 — 잡곡·쌀 종류별 물 비율·불림 타이머", "p": [{"pain": "현미·잡곡을 섞으면 물 양과 불림 시간이 감이라 밥이 되거나 질어짐", "who": "잡곡밥·솥밥 지어 먹는 사람", "when": "쌀 종류·비율을 바꿔 밥할 때", "gap": "밥솥 눈금은 백미 기준뿐 · 리이오 강점: 비율 계산 + 불림·뜸 타이머(StickyPresenter 인접)"}]},
            {"n": "🧩 레시피클립 — 영상·블로그 레시피→단계 카드", "p": [{"pain": "저장해둔 레시피 릴스를 조리 중 젖은 손으로 되감기하며 다시 봄", "who": "영상 보고 요리하는 사람", "when": "조리 중 다음 단계·계량을 확인할 때", "gap": "영상은 조리 중 탐색이 불편, 저장하면 안 봄 · 리이오 강점: 기록 UX + 큰 글씨 단계 카드(StickyPresenter 인접)"}]},
            {"n": "🧩 냉동실지도 — 냉동실 칸별 내용물 목록", "p": [{"pain": "냉동실 깊숙이 뭐가 있는지 몰라 같은 걸 또 사고, 정체불명 봉지가 화석이 됨", "who": "냉동 보관 많이 하는 가정·자취생", "when": "장보기 전·냉동실 뒤질 때", "gap": "유통기한 앱은 있어도 '어느 칸에 뭐'는 없음 · 리이오 강점: 클로즈드(장보기 연동)·기록 UX"}]},
            {"n": "🧩 커피레시피 — 홈카페 추출 레시피 기록", "p": [{"pain": "어제 맛있게 내린 원두·물량·시간 비율을 기억 못해 매번 다른 맛", "who": "핸드드립·홈카페 즐기는 사람", "when": "같은 맛을 다시 내리고 싶을 때", "gap": "메모앱은 추출 타이머와 안 이어짐 · 리이오 강점: 기록 + 타이머 결합 유틸"}]}
          ]
        }
      ]
    },
    {
      "id": "opp-pet", "icon": "🐾", "title": "반려동물 (신규 도메인)", "color": "#00b894",
      "subs": [
        {
          "title": "🌱 다뤄볼 만한 것",
          "ep": [
            {"n": "🆕🧩 밥줬냐 — 가족 공유 급여·투약 원탭 로그", "p": [{"pain": "누가 밥 줬는지 몰라 두 번 주거나 아무도 안 줌", "who": "가족이 함께 반려동물 키우는 집", "when": "밥·약 줄 때마다", "gap": "메신저로 '밥 줬어?' 묻는 게 일 · 리이오 강점: 골드위크(실시간 공유)+두번알림+원탭 위젯"}]},
            {"n": "🆕🧩 안고빼기 — 반려동물 체중 기록·성장그래프", "p": [{"pain": "저울에 안 앉는 고양이는 안고 재서 사람 몸무게를 빼는 산수를 매번 함", "who": "다이어트·건강 관리 중인 반려인", "when": "주 1회 체중 잴 때", "gap": "수동 뺄셈·기록 흩어짐 · 리이오 강점: 시각화(무지개공작소)·기록 UX"}]},
            {"n": "🆕🧩 월산충 — 월 1회 예방약 투여일 추적·알림", "p": [{"pain": "심장사상충·구충약을 이번 달 줬는지, 며칠에 줬는지 기억 안 남", "who": "예방약 챙기는 반려인", "when": "매월 투약 시점", "gap": "알림 울려도 이미 준 건지 확인 불가 · 리이오 강점: 두번알림·완료체크·기록"}]},
            {"n": "🆕🧩 펫시터카드 — 맡길 때 루틴 전달 카드", "p": [{"pain": "여행·출장 때마다 급여량·약·산책 습관·주의사항을 카톡 장문으로 새로 써서 펫시터·부모님께 보냄", "who": "반려동물을 종종 맡기는 반려인", "when": "여행·출장 전 맡길 준비할 때", "gap": "메모는 흩어지고 매번 복붙·수정 · 리이오 강점: 기록 템플릿 + 공유 카드(골드위크 공유 인접)"}]},
            {"n": "🆕🧩 산책일지 — 산책 시간·거리·배변 원탭 기록", "p": [{"pain": "오늘 산책을 했는지·얼마나 했는지 가족끼리 서로 모르고, 배변 여부도 말로 전달", "who": "산책을 나눠 맡는 반려견 가정", "when": "산책 다녀온 직후", "gap": "산책앱은 무겁고 가족 공유가 안 됨 · 리이오 강점: 원탭 로그 + 골드위크(공유) 인접"}]},
            {"n": "🆕🧩 병원수첩 — 접종·진료 기록·다음 접종 알림", "p": [{"pain": "종이 접종 수첩은 잃어버리고, 병원 옮기면 지난 진료 기록이 끊김", "who": "정기 접종·건강검진 챙기는 반려인", "when": "병원 방문·다음 접종 시기를 셈할 때", "gap": "병원마다 기록이 흩어지고 내 손엔 없음 · 리이오 강점: 기록 + 두번알림(접종 주기)"}]},
            {"n": "🆕🧩 사료계산 — 체중별 급여량·사료 소진일 예측", "p": [{"pain": "포대 사료가 언제 떨어질지 몰라 급하게 주문하고, 체중 대비 하루 급여량도 감으로 줌", "who": "사료를 정기 구매하는 반려인", "when": "사료가 바닥을 보일 때·급여량 정할 때", "gap": "급여량표는 봉투 뒷면 표뿐, 소진일 예측 없음 · 리이오 강점: 확률계산기류 계산 + 클로즈드(재구매) 인접"}]},
            {"n": "🆕🧩 모래시계 — 배변·구토 등 건강 신호 타임라인", "p": [{"pain": "병원에서 '언제부터 그랬어요?' 물으면 대답 못 함 — 구토·설사가 언제 몇 번이었는지 기억에 없음", "who": "지병·노령 반려동물 돌보는 반려인", "when": "이상 증상을 발견하고 병원 갈 때", "gap": "카톡·기억에 흩어진 증상 기록 · 리이오 강점: 원탭 타임스탬프 기록 + 시각화(패턴)"}]}
          ]
        }
      ]
    },
    {
      "id": "opp-travel", "icon": "✈️", "title": "여행 (신규 도메인)", "color": "#0984e3",
      "subs": [
        {
          "title": "🌱 다뤄볼 만한 것",
          "ep": [
            {"n": "🆕🧩 동선순 — 저장 장소를 방문 순서로 정렬", "p": [{"pain": "구글맵에 200곳 저장해도 정렬·폴더가 없어 방문 순서를 하나씩 드래그", "who": "여행 동선을 미리 짜는 J 성향 여행자", "when": "여행 전 일정·동선을 짤 때", "gap": "리스트는 정렬·경로 연결 안 됨 · 리이오 강점: 한국길찾기(지도)·정리 UX"}]},
            {"n": "🆕🧩 시차정리 — 여행 사진 촬영시각 일괄 시프트", "p": [{"pain": "카메라 시계를 현지로 안 바꿔 사진 순서가 뒤엉키고 앨범 자동분류가 깨짐", "who": "해외여행 사진 정리하는 사람", "when": "귀국 후 수백 장 정리할 때", "gap": "EXIF 시간 수동 보정은 번거로움 · 리이오 강점: 사진앱(픽셀미미/펀칭) 노하우"}]},
            {"n": "🆕🧩 얼마썼지 — 다중통화 여행 가계부", "p": [{"pain": "나라마다 통화 달라 결제할 때마다 환산·기록, 정산이 엉킴", "who": "해외·다국가 여행자, 더치페이", "when": "여행 중 결제·귀국 후 정산", "gap": "Splitwise 다중통화는 유료·엉킴 · 리이오 강점: 확률계산기류 계산 + 기록·시각화"}]},
            {"n": "🆕🧩 짐다쌌냐 — 여행 유형별 재사용 패킹 체크리스트", "p": [{"pain": "매번 메모장에 짐 목록을 처음부터 새로 적고, 그래도 충전기·어댑터를 빠뜨림", "who": "출장·여행이 잦은 사람", "when": "출발 전날 짐 쌀 때", "gap": "메모앱은 지난 여행 목록 재사용·체크 초기화가 번거로움 · 리이오 강점: 클로즈드(체크리스트) 노하우 + 템플릿 재사용"}]},
            {"n": "🆕 오프환율 — 오프라인 환율·팁 계산기", "p": [{"pain": "해외에서 데이터가 없으면 환율 계산이 막막하고, 팁 문화권에선 몇 %를 줘야 할지 매번 애매", "who": "유심 없이 다니는 여행자·팁 문화 초행자", "when": "현지 상점·식당에서 결제 직전", "gap": "환율앱 대부분 온라인 필수·팁 계산 없음 · 리이오 강점: 확률계산기류 오프라인 유틸 + 원탭 UX"}]},
            {"n": "🆕 여권체크 — 여권·비자·ESTA 만료 추적", "p": [{"pain": "여권 잔여 유효기간 6개월 룰에 걸리는 걸 공항에서야 알아 출국 못 하는 사고", "who": "해외 나갈 일이 가끔 있는 사람", "when": "항공권 예약 직전·출국 준비", "gap": "만료일을 어디에도 안 적어둠, 6개월 룰 계산도 헷갈림 · 리이오 강점: 두번알림(만료 훨씬 전부터) + D-day 계산"}]},
            {"n": "🆕 시차리듬 — 도착지 기준 수면·빛 노출 스케줄", "p": [{"pain": "장거리 비행 후 시차 적응을 감으로 해서 여행 초반 며칠을 졸며 날림", "who": "장거리 여행자·출장자", "when": "출발 며칠 전부터 도착 직후까지", "gap": "언제 자고 언제 빛을 봐야 하는지 알려주는 도구가 마땅찮음 · 리이오 강점: 달빛(수면) 확장 + 알림 스케줄"}]},
            {"n": "🆕 사다줘 — 부탁받은 기념품·선물 체크리스트", "p": [{"pain": "면세점·현지 매장에서 누가 뭘 사다 달랬는지 기억 안 나 카톡을 한참 거슬러 올라감", "who": "여행 때마다 부탁을 받는 사람", "when": "면세점·기념품 가게에서", "gap": "부탁이 카톡 여기저기 흩어짐 · 리이오 강점: 클로즈드(품목 체크) 인접 + 사람별 목록"}]},
            {"n": "🆕 체크인카드 — 항공·숙소 핵심정보 오프라인 카드", "p": [{"pain": "체크인 시간·예약번호·와이파이·주소가 메일과 앱 여기저기라 로밍 안 되는 순간 먹통", "who": "예약을 여러 앱으로 하는 여행자", "when": "공항 도착·숙소 체크인 순간", "gap": "예약앱은 오프라인·통합 뷰가 약함 · 리이오 강점: 오프라인 카드 + 위젯(당일 일정 표시)"}]},
            {"n": "🆕 도장깨기 — 가본 도시·나라 색칠 지도", "p": [{"pain": "여행 기록이 사진 폴더뿐이라 어디까지 가봤는지 한눈에 안 보이고 다음 목표도 흐릿함", "who": "여행 이력을 모으는 재미로 다니는 사람", "when": "여행 다녀온 뒤·다음 여행지 고를 때", "gap": "지도앱 저장핀은 '가봤다' 기록용이 아님 · 리이오 강점: 시각화(무지개공작소) + 인생 맛집(방문 기록) 인접"}]}
          ]
        }
      ]
    },
    {
      "id": "opp-fit", "icon": "💪", "title": "운동·건강 확장", "color": "#d63031",
      "subs": [
        {
          "title": "🌱 다뤄볼 만한 것",
          "ep": [
            {"n": "🧩 세트새 — 세트 사이 원탭·음성 운동 로그", "p": [{"pain": "세트마다 무게·횟수 타이핑하느라 쉬는 시간 절반이 날아가고 땀·초크 묻은 손엔 입력 안 됨", "who": "웨이트 기록하는 헬스인", "when": "세트 사이 쉬는 시간", "gap": "기존 앱은 탭 여러 번 · 리이오 강점: 쿨타임(습관·스트릭)·원탭 위젯 인접"}]},
            {"n": "🧩 주간볼륨 — 부위별 주간 세트·볼륨 자동 집계", "p": [{"pain": "이번 주 가슴·등 부위별 총 세트를 그래프 보며 손으로 합산", "who": "볼륨 관리하는 중급 이상 운동인", "when": "주간 루틴을 점검할 때", "gap": "앱들이 부위별 주간합을 한눈에 안 줌 · 리이오 강점: 무지개공작소류 주간 시각화"}]},
            {"n": "🧩 원판계산 — 바벨 원판 조합·단위 변환", "p": [{"pain": "목표 무게를 만들려면 '한쪽에 뭘 끼우지'를 매번 암산하고, lb 원판 헬스장에선 kg 환산까지 겹침", "who": "바벨 운동하는 헬스인", "when": "세트 사이 무게 바꿀 때", "gap": "계산기 앱은 원판 조합 개념 없음 · 리이오 강점: 확률계산기류 특화 계산 유틸"}]},
            {"n": "🧩 일어나요 — 앉은 시간 알림·30초 스트레칭", "p": [{"pain": "재택·사무직은 몇 시간을 내리 앉아 있는지 자각 못 하고 허리·목이 굳음", "who": "장시간 앉아 일하는 직장인·재택러", "when": "집중해서 일하다 보면 어느새", "gap": "일반 알람은 '앉은 시간' 기준이 아님 · 리이오 강점: 쿨타임(눈 휴식·습관화) 확장 + 짧은 가이드"}]},
            {"n": "🧩 호루라기 — 커스텀 인터벌·타바타 타이머", "p": [{"pain": "타바타·인터벌 러닝의 '20초 운동·10초 휴식'을 폰 보며 세다가 리듬이 깨짐", "who": "인터벌 트레이닝·러닝하는 사람", "when": "운동 중 구간 전환 순간", "gap": "무료 인터벌 앱은 광고가 흐름 끊음 · 리이오 강점: StickyPresenter 타이머 노하우 + 소리·햅틱 신호"}]},
            {"n": "🧩 어디아파 — 통증·컨디션 부위별 원탭 기록", "p": [{"pain": "병원에서 '언제부터 아팠어요?' 물으면 기억이 안 나고, 통증이 어떤 운동 뒤에 오는지 패턴을 모름", "who": "관절·근육 통증을 달고 사는 운동인·직장인", "when": "통증을 느낀 순간·진료 전", "gap": "메모는 부위·강도 구조가 없어 패턴이 안 보임 · 리이오 강점: 원탭 기록 + 시각화(욕망의 무지개 패턴 노하우)"}]},
            {"n": "🧩 원알엠 — 1RM 추정·퍼센트 무게 계산", "p": [{"pain": "'1RM의 75%로 5회' 프로그램을 따르려면 추정식과 퍼센트 계산을 매번 검색·암산", "who": "프로그램 따라 훈련하는 중급 리프터", "when": "오늘 들 무게를 정할 때", "gap": "계산기는 공식 선택·기록 연동이 없음 · 리이오 강점: 확률계산기류 특화 계산 + 기록"}]},
            {"n": "🧩 페이스메이커 — 목표 기록 역산 러닝 페이스", "p": [{"pain": "10K 55분 목표면 km당 몇 분으로 달려야 하는지, 중간 지점 통과 시각은 언제인지 암산이 안 됨", "who": "대회 준비하는 러너", "when": "훈련·대회 전 페이스 전략 짤 때", "gap": "러닝앱은 기록만, 역산 페이스표가 없음 · 리이오 강점: 계산 유틸 + 큰 글씨 카드(StickyPresenter 인접)"}]}
          ]
        }
      ]
    },
    {
      "id": "opp-home", "icon": "🏠", "title": "생활·환경 (정의된 문제 파생)", "color": "#636e72",
      "subs": [
        {
          "title": "🌱 다뤄볼 만한 것",
          "ep": [
            {"n": "📐 쿵쿵기록 — 층간소음 dB·시각 증거 로그", "p": [{"pain": "층간소음이 언제 얼마나 심했는지 증거가 안 남아 민원·대응이 막막", "who": "공동주택에서 층간소음 겪는 사람", "when": "밤·이른 아침 소음이 날 때", "gap": "근본해결(정의된 미해결 문제)은 아니나 '기록·증거·패턴'은 앱으로 가능 · 리이오 강점: 기록·시각화·타임스탬프"}]},
            {"n": "📐 오늘공기 — 실내외 미세먼지 비교·환기 알림", "p": [{"pain": "실외 미세먼지 나쁠 때 언제 환기할지 몰라 오히려 실내를 악화시킴", "who": "호흡기 민감·환기 챙기는 사람", "when": "미세먼지·황사 시기 하루", "gap": "실외는 근본해결 불가지만 '환기 타이밍 안내'는 가능 · 리이오 강점: 알림·위젯"}]},
            {"n": "📐 결로알림 — 이슬점 기반 결로·곰팡이 위험 안내", "p": [{"pain": "겨울마다 창틀 결로로 곰팡이가 피는데 언제 제습·환기해야 하는지 감으로 함", "who": "겨울 결로·곰팡이로 고생하는 세입자·아파트 거주자", "when": "실내외 온도차 큰 겨울·장마철", "gap": "습도 근본해결은 어려워도 '위험 시점 안내'는 가능 · 리이오 강점: 날씨 데이터 + 알림·위젯"}]},
            {"n": "🧩 버리는날 — 분리수거 요일·품목 알림", "p": [{"pain": "오늘이 재활용 버리는 날인지 매번 헷갈리고, 놓치면 일주일을 쌓아둬야 함", "who": "아파트·원룸촌에서 배출 요일 지키는 사람", "when": "저녁마다 '오늘 버려도 되나' 싶을 때", "gap": "캘린더 반복일정은 품목별(캔·병·스티로폼) 구분이 번거로움 · 리이오 강점: 두번알림 + 요일 위젯"}]},
            {"n": "🧩 갈때됐다 — 소모품 교체주기 D+일 추적", "p": [{"pain": "정수기 필터·칫솔·면도날·수세미를 언제 갈았는지 기억 안 나 늘 '너무 늦게' 교체", "who": "소모품 교체시기를 늘 놓치는 사람", "when": "'이거 언제 갈았더라' 싶을 때", "gap": "캘린더 반복은 '마지막 교체일 기준 리셋'이 안 됨 · 리이오 강점: 두번알림·잊지마 인접 + D+일 카운트업"}]},
            {"n": "🧩 빨래표 — 세탁 라벨 기호 사전·촬영 판독", "p": [{"pain": "옷 라벨의 세탁 기호를 못 읽어 니트를 세탁기에 돌렸다가 망침", "who": "빨래를 직접 하는 자취생·초보 살림러", "when": "새 옷을 처음 빨기 전", "gap": "기호표를 매번 검색하는 게 일 · 리이오 강점: 사진 판독(픽셀미미 이미지 처리) + 오프라인 사전"}]},
            {"n": "🧩 관리비어디 — 관리비·공과금 추이 시각화", "p": [{"pain": "이번 달 전기요금이 왜 많은지 지난달·작년 같은 달과 비교가 안 됨", "who": "고지서를 받고 갸웃하는 세대주", "when": "관리비 고지서·전기요금 청구 때", "gap": "고지서는 그 달 숫자뿐, 추이가 없음 · 리이오 강점: 기록·시각화(무지개공작소) + 퇴사각(재무) 인접"}]},
            {"n": "🧩 니차례 — 집안일 분담·순번 공유 보드", "p": [{"pain": "설거지·쓰레기 버리기가 누구 차례인지로 매번 실랑이하고, 한 사람에게 몰림", "who": "룸메이트·맞벌이 부부·가족", "when": "집안일이 쌓여 있는 저녁", "gap": "말로 정한 규칙은 증발함 · 리이오 강점: 골드위크(가족 공유) 인접 + 완료체크·순번 위젯"}]},
            {"n": "🧩 우산챙겨 — 내 출발시간 기준 비 알림", "p": [{"pain": "날씨앱은 확인해야 알려주고, 정작 우산은 현관을 나선 뒤에 생각남", "who": "출퇴근·등하교하는 사람", "when": "아침 집을 나서기 직전", "gap": "일반 날씨 알림은 내 출발시간·강수 시점과 안 맞음 · 리이오 강점: 두번알림(출발 전 재확인) + 위젯"}]},
            {"n": "📐 대피소어디 — 근처 대피소·행동요령 오프라인 카드", "p": [{"pain": "재난문자가 와도 어디로 가야 할지, 뭘 챙겨야 할지 모름", "who": "재난 대비를 막연히 미루는 모든 시민", "when": "지진·민방위 재난문자를 받은 순간", "gap": "재난 대비(정의된 문제)의 근본해결은 아니나 '내 위치 기준 안내'는 가능 · 리이오 강점: 한국길찾기(지도·접근성) + 오프라인 카드"}]}
          ]
        }
      ]
    },
    {
      "id": "opp-money", "icon": "💸", "title": "돈·소비 (퇴사각 인접)", "color": "#fdcb6e",
      "subs": [
        {
          "title": "🌱 다뤄볼 만한 것",
          "ep": [
            {"n": "🆕 구독털이 — 잊은 구독·갱신일 알림·연지출 시각화", "p": [{"pain": "안 쓰는 구독이 자동결제로 새어나가고 갱신일을 놓침", "who": "구독 서비스 많은 사람", "when": "갱신일 전·월말 지출 점검", "gap": "카드내역 훑어보기 번거로움 · 리이오 강점: 두번알림+FIRE(퇴사각) 재무 인접+시각화"}]},
            {"n": "🧩 영수증가계부 — 촬영→항목 자동 기록", "p": [{"pain": "영수증을 찍어도 결국 날짜·금액을 손으로 옮겨 적음", "who": "가계부·경비 정리하는 개인", "when": "지출 후 기록할 때", "gap": "스캔은 되나 입력이 수동 · 리이오 강점: 사진처리+기록 UX"}]},
            {"n": "🆕 경조사장부 — 축의금·부조 주고받은 기록", "p": [{"pain": "받은 만큼 내는 게 예의인데 몇 년 전 누가 얼마 했는지가 카톡·기억에 흩어져 매번 배우자와 설전", "who": "경조사가 잦아지는 30~40대", "when": "청첩장·부고를 받고 봉투 액수 정할 때", "gap": "가계부는 '관계별 주고받음' 조회가 안 됨 · 리이오 강점: 라포 맵(관계 기록) 인접 + 검색 UX"}]},
            {"n": "🆕 무지출스트릭 — 무지출 데이 기록·스트릭", "p": [{"pain": "아껴야지 다짐해도 오늘 무지출인지 아닌지 돌아보는 장치가 없어 흐지부지됨", "who": "절약 챌린지 중인 사람, FIRE 준비생", "when": "하루를 마감하며·충동구매 직전", "gap": "가계부는 기록용이지 동기부여가 아님 · 리이오 강점: 쿨타임(스트릭·습관화) + 퇴사각(재무 목표) 연결"}]},
            {"n": "🆕 팔림장부 — 중고 판매 등록·판매 현황 정리", "p": [{"pain": "당근·번개장터 여러 곳에 올린 물건이 뭐가 어디서 얼마에 팔렸는지 흩어져 있음", "who": "중고 거래로 짐 정리·용돈 버는 사람", "when": "물건을 올릴 때·팔린 뒤 정산할 때", "gap": "플랫폼별 내역이 통합 안 됨 · 리이오 강점: 기록·목록 UX + 수익 시각화"}]},
            {"n": "🆕 할부끝나 — 할부·약정 종료일 추적", "p": [{"pain": "폰 약정·가전 할부가 언제 끝나는지 몰라 위약금을 물거나 끝난 뒤에도 모르고 냄", "who": "할부·약정이 여러 개인 사람", "when": "기기 변경·해지를 고민할 때", "gap": "계약서는 서랍 속, 종료일은 기억 밖 · 리이오 강점: D-day + 두번알림(종료 전 알림)"}]},
            {"n": "🆕 티끌태산 — 습관 지출의 연 환산 계산기", "p": [{"pain": "하루 5천 원 커피가 1년이면 얼마인지, 그 돈을 모으면 은퇴가 얼마나 당겨지는지 체감이 안 됨", "who": "소비 습관을 바꾸고 싶은 사람, FIRE 준비생", "when": "습관성 지출 직전·소비 반성할 때", "gap": "가계부는 과거 집계뿐 미래 환산이 없음 · 리이오 강점: 퇴사각(은퇴 계산) 연결 + 불타는 내인생(소각 시각화) 노하우"}]},
            {"n": "🆕 기프티지갑 — 기프티콘·상품권 만료 관리", "p": [{"pain": "선물 받은 기프티콘이 스크린샷 더미에 묻혀 만료로 몇 만 원씩 날림", "who": "기프티콘 주고받는 모든 사람", "when": "만료 임박·매장 앞에서 '뭐 있었지' 할 때", "gap": "갤러리엔 만료일 개념이 없음 · 리이오 강점: 스크린샷 인식(찰칵정리 연계) + 두번알림(만료 전)"}]}
          ]
        }
      ]
    },
    {
      "id": "opp-sleep", "icon": "😴", "title": "수면·리듬 (달빛 확장)", "color": "#a29bfe",
      "subs": [
        {
          "title": "🌱 다뤄볼 만한 것",
          "ep": [
            {"n": "🆕 몇시에잘래 — 기상 목표 역산 취침 알림·루틴", "p": [{"pain": "일어날 시각은 정해도 언제 자야 할지 역산·습관화가 안 됨", "who": "수면 루틴을 잡고 싶은 사람", "when": "밤마다 취침 준비", "gap": "알람은 기상만, 취침 유도 없음 · 리이오 강점: 달빛(수면 사운드) 확장+두번알림"}]},
            {"n": "🆕 카페인커트 — 카페인 반감기·마지노선 알림", "p": [{"pain": "오후 커피 한 잔이 밤잠을 망치는데, 몇 시까지 마셔도 되는지는 늘 감으로 정함", "who": "커피 즐기지만 잠은 지키고 싶은 사람", "when": "오후에 커피를 마실까 말까 할 때", "gap": "카페인 반감기 계산해주는 도구가 마땅찮음 · 리이오 강점: 확률계산기류 계산 + 달빛(수면) 연결 + 알림"}]},
            {"n": "🆕 수면빚 — 주간 수면 부족 누적 시각화", "p": [{"pain": "평일에 못 잔 잠이 얼마나 쌓였는지 몰라 주말 보충도 감으로 하고 만성 피로가 됨", "who": "평일 수면이 늘 부족한 직장인·학생", "when": "주말 계획 세울 때·낮에 유난히 피곤할 때", "gap": "수면앱은 하루 단위, '누적 빚' 관점이 없음 · 리이오 강점: 무지개공작소(주간 시각화) + 달빛 연결"}]},
            {"n": "🆕 낮잠20 — 파워냅 타이머·부드러운 기상", "p": [{"pain": "점심 낮잠이 30분을 넘겨 오히려 멍해지고, 요란한 알람에 사무실에서 민망", "who": "점심시간 쪽잠 자는 직장인·수험생", "when": "점심·오후 급격히 졸릴 때", "gap": "기본 알람은 수면 관성 고려·조용한 기상이 없음 · 리이오 강점: 달빛(사운드) 확장 + 햅틱 기상"}]}
          ]
        }
      ]
    },
    {
      "id": "opp-focus", "icon": "🎯", "title": "집중·디지털 습관 (불타는 내인생 확장)", "color": "#e84393",
      "subs": [
        {
          "title": "🌱 다뤄볼 만한 것",
          "ep": [
            {"n": "🆕 딴짓카운터 — 공부 중 폰 집은 횟수 원탭 기록", "p": [{"pain": "공부·작업 중 폰을 몇 번 집었는지 자각이 없어 집중이 왜 깨지는지 모름", "who": "수험생·집중력 관리하는 직장인", "when": "공부·딥워크 세션 중", "gap": "스크린타임은 하루 합계만, '집은 횟수·타이밍'은 안 보여줌 · 리이오 강점: 불타는 내인생(시간 자각) 확장 + 원탭 위젯"}]},
            {"n": "🆕 몇분만 — 앱 열기 전 의도 확인·초과 알림", "p": [{"pain": "'딱 5분만' 하고 연 쇼츠·릴스가 정신 차리면 한 시간, 스스로 정한 상한이 없음", "who": "무한스크롤에 시간 뺏기는 사람", "when": "SNS·쇼츠 앱을 여는 순간", "gap": "스크린타임 제한은 무시하기 쉽고 의도 확인 단계가 없음 · 리이오 강점: 불타는 내인생(시간 소각 자각) + 쿨타임(절제 습관)"}]},
            {"n": "🆕 시작이반 — 미루는 일 '5분만 시작' 타이머", "p": [{"pain": "일이 무겁게 느껴져 시작을 못 하고 미루다가, 막상 시작하면 별거 아니었음을 반복", "who": "미루기 습관이 있는 학생·프리랜서", "when": "해야 할 일 앞에서 딴짓하고 있을 때", "gap": "투두앱은 '시작의 문턱'을 낮춰주지 않음 · 리이오 강점: 쿨타임(습관화) + 타이머 노하우 + 스트릭"}]},
            {"n": "🆕 폰내려놔 — 폰 뒤집으면 시작되는 집중 타이머", "p": [{"pain": "집중 타이머 앱도 결국 폰을 켜게 만들고, 폰이 시야에 있는 것만으로 집중이 샘", "who": "폰 없이 몰입하고 싶은 수험생·작업자", "when": "책상에 앉아 몰입을 시작할 때", "gap": "타이머 확인하려 폰을 보면 도루묵 · 리이오 강점: 불타는 내인생(시간 자각) + 뒤집기 감지 원탭 UX"}]}
          ]
        }
      ]
    },
    {
      "id": "opp-plant", "icon": "🪴", "title": "식물 (신규 도메인)", "color": "#00cec9",
      "subs": [
        {
          "title": "🌱 다뤄볼 만한 것",
          "ep": [
            {"n": "🆕 물줬나 — 화분별 급수 간격·마지막 급수 위젯", "p": [{"pain": "화분마다 물 주기가 달라 헷갈리고, 몬스테라는 과습으로 다육이는 건조로 죽임", "who": "화분 여러 개 키우는 식집사 초보", "when": "'오늘 물 줘야 하나' 싶을 때", "gap": "리마인더는 '마지막으로 준 날' 기준 관리가 안 됨 · 리이오 강점: 밥줬냐와 같은 원탭 로그 패턴 + D+일 위젯"}]},
            {"n": "🆕 분갈이달력 — 분갈이·영양제·가지치기 D+일 기록", "p": [{"pain": "분갈이·영양제를 언제 해줬는지 기억 안 나 시기를 놓치고, 식물별 성장 기록도 흩어짐", "who": "식물을 오래 키우고 싶은 식집사", "when": "계절 바뀌어 관리 시기가 올 때", "gap": "캘린더는 식물별 이력·사진 성장기록과 안 이어짐 · 리이오 강점: 기록·시각화 + 사진(성장앨범) 노하우"}]},
            {"n": "🆕 햇빛일기 — 자리별 일조 기록·계절 이동 알림", "p": [{"pain": "계절 따라 해 드는 자리가 바뀌는데 화분은 그대로 둬서 겨울마다 시들게 함", "who": "창가·베란다에서 식물 키우는 사람", "when": "계절이 바뀌어 볕이 달라질 때", "gap": "어느 자리에 몇 시간 볕이 드는지 기록할 도구가 없음 · 리이오 강점: 기록·시각화 + 계절 알림"}]},
            {"n": "🆕 잎사귀닥터 — 잎 상태 사진 기록·증상 체크", "p": [{"pain": "잎이 노래지는데 과습인지 볕 부족인지 몰라 커뮤니티에 물으면 답이 제각각", "who": "식물이 시들면 발만 동동 구르는 식집사", "when": "잎 색·처짐이 이상해 보일 때", "gap": "증상→원인 좁히기를 도와주는 구조화된 체크가 없음 · 리이오 강점: 사진 기록(변화 비교) + 체크리스트 UX"}]}
          ]
        }
      ]
    }
  ]
}
